c/__init__.py
c/battery_history.py
c/cli.py
c/common.py
c/overview.py
c/percent_cumulative_distribution.py
c/percent_distribution.py
c/reader.py
c/screen_on_week.py
c/stats.py
c/time_of_day.py
c/time_of_weekday.py
c/utils.py
c/voltages.py
c-0.1.0.dist-info/METADATA
c-0.1.0.dist-info/RECORD
c-0.1.0.dist-info/WHEEL
c-0.1.0.dist-info/entry_points.txt
c-0.1.0.dist-info/top_level.txt
