Metadata-Version: 2.1
Name: c
Version: 0.1.0
Summary: Android battery history analyZer
Home-page: https://github.com/1337/c
Author: Brian
Author-email: brian@ohai.ca
License: UNKNOWN
Platform: UNKNOWN
Classifier: Programming Language :: Python :: 3
Classifier: License :: OSI Approved :: GNU General Public License v3 (GPLv3)
Classifier: Operating System :: POSIX :: Linux
